tracking_policy_agendas/__init__.py
tracking_policy_agendas/api.py
tracking_policy_agendas/classifiers/__init__.py
tracking_policy_agendas/classifiers/lasso_clf.py
tracking_policy_agendas/classifiers/meta_clf.py
tracking_policy_agendas/classifiers/meta_sklearn_clf.py
tracking_policy_agendas/classifiers/naive_bayes_clf.py
tracking_policy_agendas/classifiers/pa_clf.py
tracking_policy_agendas/classifiers/xgb_clf.py
tracking_policy_agendas/word2vec/__init__.py
tracking_policy_agendas/word2vec/w2v_corpus.py
tracking_policy_agendas/word2vec/w2v_emb.py
tracking_policy_agendas-1.0.0.dist-info/LICENSE
tracking_policy_agendas-1.0.0.dist-info/METADATA
tracking_policy_agendas-1.0.0.dist-info/WHEEL
tracking_policy_agendas-1.0.0.dist-info/top_level.txt
tracking_policy_agendas-1.0.0.dist-info/RECORD
