Metadata-Version: 2.1
Name: tracking-policy-agendas
Version: 1.0.0
Summary: A Persian Twitter policy agenda tracking framework
Home-page: https://github.com/MohammadForouhesh/tracking-policy-agendas
Author: MohammadForouhesh
Author-email: Mohammadh.Forouhesh@gmail.com
License: MIT
Keywords: NLP,Computational Social Science,Agenda Setting
Platform: UNKNOWN
Classifier: License :: OSI Approved :: MIT License
Classifier: Programming Language :: Python :: 3
Classifier: Programming Language :: Python :: 3.7
Classifier: Programming Language :: Python :: 3.8
Classifier: Programming Language :: Python :: 3.9
Requires-Python: >=3.8
License-File: LICENSE
Requires-Dist: pandas (>=1.3.5)
Requires-Dist: tqdm (>=4.62.3)
Requires-Dist: gensim (>=4.1.2)
Requires-Dist: numpy (>=1.21.5)
Requires-Dist: scikit-learn (>=1.0.2)
Requires-Dist: matplotlib (>=3.5.1)
Requires-Dist: xgboost (>=1.5.0)
Requires-Dist: pytest (>=6.2.5)
Requires-Dist: coverage (>=6.2)
Requires-Dist: requests (>=2.26.0)
